odoo/addons/l10n_ro_dvi/README.rst
odoo/addons/l10n_ro_dvi/__init__.py
odoo/addons/l10n_ro_dvi/__manifest__.py
odoo/addons/l10n_ro_dvi/i18n/l10n_ro_dvi.pot
odoo/addons/l10n_ro_dvi/i18n/ro.po
odoo/addons/l10n_ro_dvi/migrations/14.0.1.0.1/pre-migration.py
odoo/addons/l10n_ro_dvi/migrations/14.0.1.10.1/pre-migration.py
odoo/addons/l10n_ro_dvi/models/__init__.py
odoo/addons/l10n_ro_dvi/models/account_invoice.py
odoo/addons/l10n_ro_dvi/models/l10n_ro_account_dvi.py
odoo/addons/l10n_ro_dvi/models/res_company.py
odoo/addons/l10n_ro_dvi/models/stock_landed_cost.py
odoo/addons/l10n_ro_dvi/readme/CONTRIBUTORS.rst
odoo/addons/l10n_ro_dvi/readme/DESCRIPTION.rst
odoo/addons/l10n_ro_dvi/readme/USAGE.rst
odoo/addons/l10n_ro_dvi/security/ir.model.access.csv
odoo/addons/l10n_ro_dvi/static/description/icon.png
odoo/addons/l10n_ro_dvi/static/description/icon.svg
odoo/addons/l10n_ro_dvi/static/description/index.html
odoo/addons/l10n_ro_dvi/tests/__init__.py
odoo/addons/l10n_ro_dvi/tests/test_dvi.py
odoo/addons/l10n_ro_dvi/views/account_dvi_view.xml
odoo/addons/l10n_ro_dvi/views/account_invoice_view.xml
odoo/addons/l10n_ro_dvi/views/stock_landed_cost_view.xml
odoo14_addon_l10n_ro_dvi-14.0.1.16.0.dist-info/METADATA
odoo14_addon_l10n_ro_dvi-14.0.1.16.0.dist-info/WHEEL
odoo14_addon_l10n_ro_dvi-14.0.1.16.0.dist-info/top_level.txt
odoo14_addon_l10n_ro_dvi-14.0.1.16.0.dist-info/RECORD
